MANIFEST.in
README.rst
requirements.txt
setup.py
pantera/__init__.py
pantera/chaos.py
pantera.egg-info/PKG-INFO
pantera.egg-info/SOURCES.txt
pantera.egg-info/dependency_links.txt
pantera.egg-info/requires.txt
pantera.egg-info/top_level.txt