Metadata-Version: 1.0
Name: pantera
Version: 0.2
Summary: tool to add some chaos to tsuru PaaS
Home-page: UNKNOWN
Author: timeredbull
Author-email: timeredbull@corp.globo.com
License: UNKNOWN
Platform: UNKNOWN
